oq_wrapper/__init__.py
oq_wrapper/constants.py
oq_wrapper/estimations.py
oq_wrapper/wrapper.py
oq_wrapper/examples/run_emp_gmm.py
oq_wrapper/examples/run_emp_gmm_logic_tree.py
oq_wrapper/gmm_logic_tree_configs/nhm_2010_bb_config.yaml
oq_wrapper/gmm_logic_tree_configs/nshm_2022_config.yaml
oq_wrapper/scripts/one_offs/README.txt
oq_wrapper/scripts/one_offs/ga11_vertical_spectra.py
oq_wrapper/scripts/one_offs/nzshm_residuals.py
oq_wrapper-2025.12.4.dist-info/METADATA
oq_wrapper-2025.12.4.dist-info/WHEEL
oq_wrapper-2025.12.4.dist-info/top_level.txt
oq_wrapper-2025.12.4.dist-info/RECORD
