Metadata-Version: 2.4
Name: oq-wrapper
Version: 2025.12.4
Summary: Wrapper for OpenQuake engine to run empirical GMMs
Author: ucgmsim
Requires-Python: >=3.11
Requires-Dist: numpy
Requires-Dist: openquake.engine
Requires-Dist: pandas[pyarrow]
Requires-Dist: pyyaml
Requires-Dist: scipy>=1.7.2
Requires-Dist: source-modelling
Provides-Extra: test
Requires-Dist: pytest; extra == "test"
Provides-Extra: dev
Requires-Dist: ruff; extra == "dev"
Requires-Dist: deptry; extra == "dev"
Requires-Dist: ty; extra == "dev"
